frontend/README.md
scripts/build_frontend.py
zen_sight/__init__.py
zen_sight/adapters.py
zen_sight/server.py
zen_sight/sight.py
zen_sight/static/index.html
zen_sight/static/vite.svg
zen_sight/static/assets/index-C6jBIbNX.js
zen_sight/static/assets/index-RLWRYcB4.css
zen_sight-0.2.1.dist-info/METADATA
zen_sight-0.2.1.dist-info/WHEEL
zen_sight-0.2.1.dist-info/top_level.txt
zen_sight-0.2.1.dist-info/RECORD
