Metadata-Version: 2.4
Name: zen-sight
Version: 0.2.1
Summary: A 3D simplicial complex visualizer
Requires-Python: >=3.11
Requires-Dist: flask>=3.1.0
Requires-Dist: flask-cors>=5.0.0
Requires-Dist: networkx>=3.4.2
Requires-Dist: numpy>=2.2.5
Requires-Dist: zen-mapper>=0.3.0
